torch_bench_gpu.py
torch_bench_gpu-0.1.3.dist-info/METADATA
torch_bench_gpu-0.1.3.dist-info/WHEEL
torch_bench_gpu-0.1.3.dist-info/entry_points.txt
torch_bench_gpu-0.1.3.dist-info/RECORD
