Metadata-Version: 2.4
Name: torch_bench_gpu
Version: 0.1.3
Summary: Tiny PyTorch GPU-benchmark CLI
Author-email: Arnaud Pannatier <arn.pannatier@gmail.com>
Requires-Python: >=3.8
Requires-Dist: torch>=2.8.0.dev20250515
Requires-Dist: torchao>=0.12.0.dev20250515
